MANIFEST.in
setup.py
bampy/__init__.py
bampy/__version.py
bampy/reader.py
bampy/reference.py
bampy/sam.py
bampy/util.py
bampy/writer.py
bampy.egg-info/PKG-INFO
bampy.egg-info/SOURCES.txt
bampy.egg-info/dependency_links.txt
bampy.egg-info/top_level.txt
bampy/bam/__init__.py
bampy/bam/packed_cigar.py
bampy/bam/packed_sequence.py
bampy/bam/record.py
bampy/bam/tag.py
bampy/bam/util.py
bampy/bgzf/__init__.py
bampy/bgzf/block.py
bampy/bgzf/reader.py
bampy/bgzf/util.py
bampy/bgzf/writer.py
bampy/bgzf/zlib.py