Metadata-Version: 1.0
Name: bampy
Version: 0.1.0
Summary: Python implementation of htslib supporting BAM, SAM, and BGZF compression
Home-page: https://github.com/innovate-invent/bampy
Author: Nolan
Author-email: nolan@i2labs.ca
License: MIT
Platform: UNKNOWN
